lazyins/__init__.py
lazyins/lazyins.py
lazyins-0.1.1.dist-info/LICENSE
lazyins-0.1.1.dist-info/METADATA
lazyins-0.1.1.dist-info/WHEEL
lazyins-0.1.1.dist-info/top_level.txt
lazyins-0.1.1.dist-info/RECORD
