Metadata-Version: 2.1
Name: lazyins
Version: 0.1.1
Summary: A stupid MySQL insert helper
Home-page: https://github.com/mzks/lazyins
Author: Keita Mizukoshi
Author-email: keita@mzks.dev
Project-URL: Bug Tracker, https://github.com/mzks/lazyins/issue
Classifier: Programming Language :: Python :: 3
Classifier: License :: OSI Approved :: MIT License
Classifier: Operating System :: OS Independent
License-File: LICENSE
